ironic_staging_drivers/__init__.py
ironic_staging_drivers/version.py
ironic_staging_drivers/amt/__init__.py
ironic_staging_drivers/amt/common.py
ironic_staging_drivers/amt/drivers.py
ironic_staging_drivers/amt/management.py
ironic_staging_drivers/amt/other-requirements.sh
ironic_staging_drivers/amt/power.py
ironic_staging_drivers/amt/resource_uris.py
ironic_staging_drivers/common/__init__.py
ironic_staging_drivers/common/exception.py
ironic_staging_drivers/common/i18n.py
ironic_staging_drivers/common/utils.py
ironic_staging_drivers/iboot/__init__.py
ironic_staging_drivers/iboot/power.py
ironic_staging_drivers/intel_nm/__init__.py
ironic_staging_drivers/intel_nm/control_schema.json
ironic_staging_drivers/intel_nm/get_cap_schema.json
ironic_staging_drivers/intel_nm/main_ids_schema.json
ironic_staging_drivers/intel_nm/nm_commands.py
ironic_staging_drivers/intel_nm/nm_vendor.py
ironic_staging_drivers/intel_nm/policy_schema.json
ironic_staging_drivers/intel_nm/statistics_schema.json
ironic_staging_drivers/intel_nm/suspend_schema.json
ironic_staging_drivers/libvirt/__init__.py
ironic_staging_drivers/libvirt/power.py
ironic_staging_drivers/libvirt/python-requirements.txt
ironic_staging_drivers/ovirt/__init__.py
ironic_staging_drivers/ovirt/other-requirements.sh
ironic_staging_drivers/ovirt/ovirt.py
ironic_staging_drivers/ovirt/python-requirements.txt
ironic_staging_drivers/tests/__init__.py
ironic_staging_drivers/tests/unit/__init__.py
ironic_staging_drivers/tests/unit/third_party_driver_mock_specs.py
ironic_staging_drivers/tests/unit/third_party_driver_mocks.py
ironic_staging_drivers/tests/unit/utils.py
ironic_staging_drivers/tests/unit/amt/__init__.py
ironic_staging_drivers/tests/unit/amt/pywsman_mocks.py
ironic_staging_drivers/tests/unit/amt/pywsman_mocks_specs.py
ironic_staging_drivers/tests/unit/amt/test_common.py
ironic_staging_drivers/tests/unit/amt/test_management.py
ironic_staging_drivers/tests/unit/amt/test_power.py
ironic_staging_drivers/tests/unit/amt/utils.py
ironic_staging_drivers-0.17.0.dist-info/AUTHORS
ironic_staging_drivers-0.17.0.dist-info/LICENSE
ironic_staging_drivers-0.17.0.dist-info/METADATA
ironic_staging_drivers-0.17.0.dist-info/WHEEL
ironic_staging_drivers-0.17.0.dist-info/entry_points.txt
ironic_staging_drivers-0.17.0.dist-info/pbr.json
ironic_staging_drivers-0.17.0.dist-info/top_level.txt
ironic_staging_drivers-0.17.0.dist-info/RECORD
