Metadata-Version: 2.1
Name: ironic-staging-drivers
Version: 0.17.0
Summary: A project used to hold out-of-tree ironic drivers
Home-page: https://ironic-staging-drivers.readthedocs.io/en/latest/
Author: OpenStack
Author-email: openstack-discuss@lists.openstack.org
License: UNKNOWN
Platform: UNKNOWN
Classifier: Environment :: OpenStack
Classifier: Intended Audience :: Information Technology
Classifier: Intended Audience :: System Administrators
Classifier: License :: OSI Approved :: Apache Software License
Classifier: Operating System :: POSIX :: Linux
Classifier: Programming Language :: Python
Classifier: Programming Language :: Python :: 3 :: Only
Classifier: Programming Language :: Python :: 3
Classifier: Programming Language :: Python :: 3.6
Classifier: Programming Language :: Python :: 3.7
Classifier: Programming Language :: Python :: 3.8
Classifier: Programming Language :: Python :: 3.9
Requires-Dist: ironic-lib (>=2.17.1)
Requires-Dist: jsonschema (>=2.6.0)
Requires-Dist: oslo.concurrency (>=3.26.0)
Requires-Dist: oslo.config (>=5.2.0)
Requires-Dist: oslo.i18n (>=3.15.3)
Requires-Dist: oslo.log (>=3.36.0)
Requires-Dist: oslo.service (!=1.28.1,>=1.24.0)
Requires-Dist: oslo.utils (>=3.40.0)
Requires-Dist: pbr (!=2.1.0,>=2.0.0)
